LICENSE
README.md
setup.py
stanag4586edav1/__init__.py
stanag4586edav1/message01.py
stanag4586edav1/message1200.py
stanag4586edav1/message20.py
stanag4586edav1/message200.py
stanag4586edav1/message20000.py
stanag4586edav1/message20010.py
stanag4586edav1/message20020.py
stanag4586edav1/message20030.py
stanag4586edav1/message20040.py
stanag4586edav1/message201.py
stanag4586edav1/message21.py
stanag4586edav1/message300.py
stanag4586edav1/message301.py
stanag4586edav1/message302.py
stanag4586edav1/message_base.py
stanag4586edav1/message_wrapper.py
stanag4586edav1.egg-info/PKG-INFO
stanag4586edav1.egg-info/SOURCES.txt
stanag4586edav1.egg-info/dependency_links.txt
stanag4586edav1.egg-info/top_level.txt