Metadata-Version: 2.1
Name: stanag4586edav1
Version: 0.0.15
Summary: Python Stanag 4586 Edition A v1
Home-page: https://github.com/faisalthaheem/python-stanag-4586-EDA-v1
Author: Faisal Thaheem
License: GPLV3
Platform: UNKNOWN
Classifier: License :: OSI Approved :: GNU General Public License v3 (GPLv3)
Classifier: Programming Language :: Python :: 3
License-File: LICENSE
